allure_pytest_bdd/__init__.py
allure_pytest_bdd/allure_api_listener.py
allure_pytest_bdd/plugin.py
allure_pytest_bdd/pytest_bdd_listener.py
allure_pytest_bdd/steps.py
allure_pytest_bdd/storage.py
allure_pytest_bdd/utils.py
allure_pytest_bdd-2.15.3.dist-info/METADATA
allure_pytest_bdd-2.15.3.dist-info/WHEEL
allure_pytest_bdd-2.15.3.dist-info/entry_points.txt
allure_pytest_bdd-2.15.3.dist-info/top_level.txt
allure_pytest_bdd-2.15.3.dist-info/RECORD
